CHANGES.txt
MANIFEST.in
README.txt
setup.py
docs/LICENSE.GPL
docs/LICENSE.txt
src/collective/__init__.py
src/collective.favorites.egg-info/PKG-INFO
src/collective.favorites.egg-info/SOURCES.txt
src/collective.favorites.egg-info/dependency_links.txt
src/collective.favorites.egg-info/entry_points.txt
src/collective.favorites.egg-info/namespace_packages.txt
src/collective.favorites.egg-info/not-zip-safe
src/collective.favorites.egg-info/requires.txt
src/collective.favorites.egg-info/top_level.txt
src/collective/favorites/__init__.py
src/collective/favorites/actions.py
src/collective/favorites/configure.zcml
src/collective/favorites/interfaces.py
src/collective/favorites/storage.py
src/collective/favorites/switchfavorite.pt
src/collective/favorites/testing.py
src/collective/favorites/viewlet.py
src/collective/favorites/locales/collective.favorites-manual.pot
src/collective/favorites/locales/collective.favorites.pot
src/collective/favorites/locales/plone-manual.pot
src/collective/favorites/locales/update.sh
src/collective/favorites/locales/de/LC_MESSAGES/collective.favorites.po
src/collective/favorites/locales/de/LC_MESSAGES/plone.po
src/collective/favorites/locales/es/LC_MESSAGES/collective.favorites.po
src/collective/favorites/locales/es/LC_MESSAGES/plone.po
src/collective/favorites/locales/fr/LC_MESSAGES/collective.favorites.po
src/collective/favorites/locales/fr/LC_MESSAGES/plone.po
src/collective/favorites/locales/it/LC_MESSAGES/collective.favorites.po
src/collective/favorites/locales/it/LC_MESSAGES/plone.po
src/collective/favorites/locales/jp/LC_MESSAGES/collective.favorites.po
src/collective/favorites/locales/jp/LC_MESSAGES/plone.po
src/collective/favorites/locales/nl/LC_MESSAGES/collective.favorites.po
src/collective/favorites/locales/pt/LC_MESSAGES/collective.favorites.po
src/collective/favorites/locales/pt/LC_MESSAGES/plone.po
src/collective/favorites/locales/ru/LC_MESSAGES/collective.favorites.mo
src/collective/favorites/locales/ru/LC_MESSAGES/collective.favorites.po
src/collective/favorites/locales/ru/LC_MESSAGES/plone.mo
src/collective/favorites/locales/ru/LC_MESSAGES/plone.po
src/collective/favorites/locales/uk/LC_MESSAGES/collective.favorites.mo
src/collective/favorites/locales/uk/LC_MESSAGES/collective.favorites.po
src/collective/favorites/locales/uk/LC_MESSAGES/plone.mo
src/collective/favorites/locales/uk/LC_MESSAGES/plone.po
