Metadata-Version: 1.1
Name: collective.favorites
Version: 1.1.7
Summary: An extensible favorites system for Plone, with a portlet
Home-page: https://github.com/collective/collective.favorites
Author: Thomas Desvenain
Author-email: thomas.desvenain@gmail.com
License: gpl
Keywords: portlet favorites favourites document management
Platform: UNKNOWN
Classifier: Environment :: Web Environment
Classifier: Framework :: Plone
Classifier: Framework :: Plone :: 4.0
Classifier: Framework :: Plone :: 4.1
Classifier: Framework :: Plone :: 4.2
Classifier: Framework :: Plone :: 4.3
Classifier: Programming Language :: Python
Classifier: Programming Language :: Python :: 2.7
Classifier: Programming Language :: Python :: 2.6
